[
  {
    "reported_at": "2025-10-01T11:28:34.024024+02:00",
    "accuracy": null,
    "lat": 50.77774113674314,
    "lon": 6.066384431272361
  },
  {
    "reported_at": "2025-10-01T11:29:12+02:00",
    "accuracy": 52.0,
    "lat": 50.7767784,
    "lon": 6.0682215
  },
  {
    "reported_at": "2025-10-01T11:29:37+02:00",
    "accuracy": 61.0,
    "lat": 50.776669,
    "lon": 6.0714771
  },
  {
    "reported_at": "2025-10-01T11:40:08+02:00",
    "accuracy": 73.0,
    "lat": 50.7585396,
    "lon": 6.0832239
  },
  {
    "reported_at": "2025-10-01T11:40:13+02:00",
    "accuracy": 98.0,
    "lat": 50.7582514,
    "lon": 6.0830171
  },
  {
    "reported_at": "2025-10-01T11:40:18+02:00",
    "accuracy": 98.0,
    "lat": 50.7582514,
    "lon": 6.0830171
  },
  {
    "reported_at": "2025-10-01T12:35:29.913179+02:00",
    "accuracy": null,
    "lat": 50.75929956866233,
    "lon": 6.082165213062647
  }
]
